{"base_url":"","routes":{"bazinga_jstranslation_js":{"tokens":[["variable",".","js|json","_format",true],["variable","\/","[\\w]+","domain",true],["text","\/translations"]],"defaults":{"domain":"messages","_format":"js"},"requirements":{"_format":"js|json","domain":"[\\w]+"},"hosttokens":[],"methods":["GET"],"schemes":[]},"app_index":{"tokens":[["text","\/"]],"defaults":[],"requirements":[],"hosttokens":[],"methods":[],"schemes":[]},"app_library_index":{"tokens":[["text","\/library"]],"defaults":[],"requirements":[],"hosttokens":[],"methods":[],"schemes":[]},"app_library_search":{"tokens":[["variable","\/","[^\/]++","q",true],["text","\/library\/search"]],"defaults":[],"requirements":[],"hosttokens":[],"methods":[],"schemes":[]},"app_library_score_show":{"tokens":[["variable","\/","[^\/]++","id",true],["text","\/library\/score"]],"defaults":[],"requirements":[],"hosttokens":[],"methods":["GET"],"schemes":[]},"app_library_score_edit":{"tokens":[["text","\/edit"],["variable","\/","[^\/]++","id",true],["text","\/library\/score"]],"defaults":[],"requirements":[],"hosttokens":[],"methods":["GET"],"schemes":[]},"app_library_score_new":{"tokens":[["text","\/library\/score\/new"]],"defaults":[],"requirements":[],"hosttokens":[],"methods":["GET"],"schemes":[]},"app_library_scorefile_download_all":{"tokens":[["text","\/download\/all"],["variable","\/","[^\/]++","score",true],["text","\/library\/score"]],"defaults":[],"requirements":[],"hosttokens":[],"methods":[],"schemes":[]},"app_library_scorefile_download":{"tokens":[["variable","\/","[^\/]++","scoreFile",true],["text","\/download"],["variable","\/","[^\/]++","score",true],["text","\/library\/score"]],"defaults":[],"requirements":[],"hosttokens":[],"methods":[],"schemes":[]},"app_lisiting_index":{"tokens":[["text","\/listing"]],"defaults":[],"requirements":[],"hosttokens":[],"methods":[],"schemes":[]},"app_listing_list":{"tokens":[["text","\/listing\/list"]],"defaults":[],"requirements":[],"hosttokens":[],"methods":[],"schemes":[]},"app_listing_new":{"tokens":[["text","\/listing\/new"]],"defaults":[],"requirements":[],"hosttokens":[],"methods":["GET"],"schemes":[]},"app_listing_show":{"tokens":[["variable","\/","[^\/]++","id",true],["text","\/listing\/show"]],"defaults":[],"requirements":[],"hosttokens":[],"methods":["GET"],"schemes":[]},"app_listing_edit":{"tokens":[["variable","\/","[^\/]++","id",true],["text","\/listing\/edit"]],"defaults":[],"requirements":[],"hosttokens":[],"methods":["GET"],"schemes":[]},"app_login":{"tokens":[["text","\/login"]],"defaults":[],"requirements":[],"hosttokens":[],"methods":[],"schemes":[]},"app_register":{"tokens":[["text","\/register"]],"defaults":[],"requirements":[],"hosttokens":[],"methods":[],"schemes":[]},"app_logout":{"tokens":[["text","\/logout"]],"defaults":[],"requirements":[],"hosttokens":[],"methods":[],"schemes":[]}},"prefix":"","host":"localhost","port":"","scheme":"http","locale":""}